README.txt
setup.py
docs/HISTORY.txt
docs/INSTALL.txt
docs/LICENSE.GPL
docs/LICENSE.txt
src/plone/__init__.py
src/plone.testlayers.egg-info/PKG-INFO
src/plone.testlayers.egg-info/SOURCES.txt
src/plone.testlayers.egg-info/dependency_links.txt
src/plone.testlayers.egg-info/namespace_packages.txt
src/plone.testlayers.egg-info/not-zip-safe
src/plone.testlayers.egg-info/requires.txt
src/plone.testlayers.egg-info/top_level.txt
src/plone/testlayers/__init__.py
src/plone/testlayers/configure.zcml
src/plone/testlayers/profiles/default/metadata.xml
src/plone/testlayers/tests/__init__.py
src/plone/testlayers/tests/base.py
src/plone/testlayers/tests/test_bar.py
src/plone/testlayers/tests/test_foo.py
src/plone/testlayers/tests/test_pony.py