Metadata-Version: 1.0
Name: plone.testlayers
Version: 1.0a3
Summary: Painless setup of Plone integration test layers
Home-page: http://pypi.python.org/pypi/plone.testlayers
Author: Andreas Zeidler
Author-email: az@zitc.de
License: GPL
Keywords: plone testing layers
Platform: Any
Classifier: Development Status :: 3 - Alpha
Classifier: Environment :: Web Environment
Classifier: Framework :: Plone
Classifier: Intended Audience :: Developers
Classifier: Intended Audience :: Other Audience
Classifier: License :: OSI Approved :: GNU General Public License (GPL)
Classifier: Operating System :: OS Independent
Classifier: Programming Language :: Python
Classifier: Topic :: Software Development :: Libraries :: Python Modules
